cxsq/__init__.py
cxsq/__main__.py
cxsq/cxsq.py
cxsq-0.2.0.dist-info/METADATA
cxsq-0.2.0.dist-info/WHEEL
cxsq-0.2.0.dist-info/entry_points.txt
cxsq-0.2.0.dist-info/top_level.txt
cxsq-0.2.0.dist-info/RECORD
